edx_analytics_logger/__init__.py
edx_analytics_logger/api.py
edx_analytics_logger-1.2.1.dist-info/LICENSE
edx_analytics_logger-1.2.1.dist-info/METADATA
edx_analytics_logger-1.2.1.dist-info/WHEEL
edx_analytics_logger-1.2.1.dist-info/top_level.txt
edx_analytics_logger-1.2.1.dist-info/RECORD
