Metadata-Version: 2.1
Name: edx-analytics-logger
Version: 1.2.1
Summary: edx powered ApiBackend
Home-page: https://github.com/javi-aranda/edx-analytics-logger
Author: javisenberg
License: MIT
License-File: LICENSE
Requires-Dist: celery
Requires-Dist: requests
